textrix/__init__.py
textrix/text_utils.py
Textrix-0.1.0.dist-info/LICENSE
Textrix-0.1.0.dist-info/METADATA
Textrix-0.1.0.dist-info/WHEEL
Textrix-0.1.0.dist-info/top_level.txt
Textrix-0.1.0.dist-info/RECORD
