Metadata-Version: 2.1
Name: Textrix
Version: 0.1.0
Summary: A text processing utility package
Home-page: https://github.com/priyanshi58/Textrix
Author: Priyanshi Mehta
Author-email: dhwani2003@gmail.com
Classifier: Programming Language :: Python :: 3
Classifier: License :: OSI Approved :: MIT License
Classifier: Operating System :: OS Independent
Requires-Python: >=3.6
License-File: LICENSE
